LICENSE
MANIFEST.in
README.md
pyproject.toml
setup.cfg
setup.py
docassemble.AKA2JBranding.egg-info/PKG-INFO
docassemble.AKA2JBranding.egg-info/SOURCES.txt
docassemble.AKA2JBranding.egg-info/dependency_links.txt
docassemble.AKA2JBranding.egg-info/not-zip-safe
docassemble.AKA2JBranding.egg-info/requires.txt
docassemble.AKA2JBranding.egg-info/top_level.txt
docassemble/AKA2JBranding/__init__.py
docassemble/AKA2JBranding/advertise_weaver.py
docassemble/AKA2JBranding/ak_document.py
docassemble/AKA2JBranding/al_courts.py
docassemble/AKA2JBranding/data/questions/aka2j_mod_cust_div_templates.yml
docassemble/AKA2JBranding/data/questions/aka2j_motion_response_templates.yml
docassemble/AKA2JBranding/data/questions/aka2j_templates.yml
docassemble/AKA2JBranding/data/questions/custom_organization.yml
docassemble/AKA2JBranding/data/questions/custom_organization_demo.yml
docassemble/AKA2JBranding/data/questions/custom_organization_that_comes_w_package.yml
docassemble/AKA2JBranding/data/questions/feedback.yml
docassemble/AKA2JBranding/data/questions/question_for_testing_feedback_form.yml
docassemble/AKA2JBranding/data/questions/recaptcha.yml
docassemble/AKA2JBranding/data/questions/terms_of_use.yml
docassemble/AKA2JBranding/data/questions/view_courts.yml
docassemble/AKA2JBranding/data/sources/README.md
docassemble/AKA2JBranding/data/sources/configuration_capabilities.yml
docassemble/AKA2JBranding/data/sources/court_sample.xlsx
docassemble/AKA2JBranding/data/static/CertOfDistr_interim_child_support.png
docassemble/AKA2JBranding/data/static/CertOfDistrib_dissolution.PNG
docassemble/AKA2JBranding/data/static/CertOfDistrib_divorce_custody.PNG
docassemble/AKA2JBranding/data/static/README.md
docassemble/AKA2JBranding/data/static/acs_logo.jpg
docassemble/AKA2JBranding/data/static/acs_logo.png
docassemble/AKA2JBranding/data/static/certofservice.png
docassemble/AKA2JBranding/data/static/certofservice_enforce.png
docassemble/AKA2JBranding/data/static/certofservice_interim_orders.png
docassemble/AKA2JBranding/data/static/certofservice_mod_motion_response_dr_725.PNG
docassemble/AKA2JBranding/data/static/certofservice_modify.png
docassemble/AKA2JBranding/data/static/certofservice_motion_response_civ_810.PNG
docassemble/AKA2JBranding/data/static/certofservice_motion_shc_1300.png
