Metadata-Version: 2.4
Name: docassemble.AKA2JBranding
Version: 25.7.19
Summary: Package to customize Alaska jurisdiction's needs
Home-page: https://docassemble.org
Author: Caroline Robinson
Author-email: CRobinson@AKcourts.gov
License: The MIT License (MIT)
License-File: LICENSE
Requires-Dist: docassemble.AssemblyLine>=3.5.1
Dynamic: author
Dynamic: author-email
Dynamic: description
Dynamic: description-content-type
Dynamic: home-page
Dynamic: license
Dynamic: license-file
Dynamic: requires-dist
Dynamic: summary
